txrequest/__init__.py
txrequest/_headers.py
txrequest/_request.py
txrequest/_version.py
txrequest/test/__init__.py
txrequest/test/_legacy_request.py
txrequest/test/_strategies.py
txrequest/test/_trial.py
txrequest/test/test_headers.py
txrequest/test/test_request.py
txrequest-0.1.0.dist-info/DESCRIPTION.rst
txrequest-0.1.0.dist-info/METADATA
txrequest-0.1.0.dist-info/RECORD
txrequest-0.1.0.dist-info/WHEEL
txrequest-0.1.0.dist-info/entry_points.txt
txrequest-0.1.0.dist-info/metadata.json
txrequest-0.1.0.dist-info/top_level.txt
