Metadata-Version: 2.0
Name: txrequest
Version: 0.1.0
Summary: HTTP Request object API for Twisted
Home-page: https://github.com/wsanchez/txrequest
Author: Wilfredo Sánchez Vega
Author-email: wsanchez@twistedmatrix.com
License: MIT
Keywords: twisted web http request
Platform: all
Classifier: Framework :: Twisted
Classifier: Intended Audience :: Developers
Classifier: License :: OSI Approved :: MIT License
Classifier: Operating System :: OS Independent
Classifier: Programming Language :: Python :: 2.7
Classifier: Programming Language :: Python :: 3.4
Classifier: Programming Language :: Python :: 3.5
Classifier: Programming Language :: Python :: 3.6
Classifier: Topic :: Software Development :: Libraries :: Python Modules
Requires-Python: >=2.7, !=3.0.*, !=3.1.*, !=3.2.*, !=3.3.*, <4
Requires-Dist: attrs
Requires-Dist: hyperlink
Requires-Dist: incremental
Requires-Dist: tubes
Requires-Dist: twisted
Requires-Dist: typing
Requires-Dist: zope.interface
